abatcher/main.py
abatcher/__init__.py
abatcher-0.2.0.dist-info/WHEEL
abatcher-0.2.0.dist-info/METADATA
abatcher-0.2.0.dist-info/RECORD
