Metadata-Version: 2.3
Name: abatcher
Version: 0.2.0
Summary: Parallel HTTP request batcher with rate limiting, retries, connection pooling, and more.
Author: David Gasquez
Author-email: David Gasquez <davidgasquez@gmail.com>
Requires-Dist: aiometer>=1.0.0
Requires-Dist: httpx>=0.28.1
Requires-Dist: tenacity>=9.1.2
Requires-Python: >=3.12
